huunifie/__init__.py
huunifie/__main__.py
huunifie-0.4.3.dist-info/LICENSE
huunifie-0.4.3.dist-info/METADATA
huunifie-0.4.3.dist-info/WHEEL
huunifie-0.4.3.dist-info/top_level.txt
huunifie-0.4.3.dist-info/RECORD
