Metadata-Version: 2.1
Name: huunifie
Version: 0.4.3
Summary: A Hue bridge and Unifi controller client.
Home-page: https://github.com/KurisuD/huunifie
Author: KurisuD
Author-email: KurisuD@pypi.darnand.net
License: UNKNOWN
Platform: UNKNOWN
Classifier: Programming Language :: Python :: 3 :: Only
Classifier: Programming Language :: Python :: 3.5
Classifier: License :: Public Domain
Classifier: Operating System :: OS Independent
Classifier: Topic :: Home Automation
Requires-Dist: pathlib
Requires-Dist: requests
Requires-Dist: pap-logger
Requires-Dist: argparse
